setup.py
oxyba/__init__.py
oxyba.egg-info/PKG-INFO
oxyba.egg-info/SOURCES.txt
oxyba.egg-info/dependency_links.txt
oxyba.egg-info/not-zip-safe
oxyba.egg-info/requires.txt
oxyba.egg-info/top_level.txt