Metadata-Version: 1.2
Name: oxyba
Version: 0.32.0
Summary: deprecated
Home-page: http://github.com/kmedian
Author: Ulf Hamster
Author-email: 554c46@gmail.com
License: MIT
Platform: UNKNOWN
Requires-Python: >=3.6
